gitlab_versioned_pages/__init__.py
gitlab_versioned_pages/__main__.py
gitlab_versioned_pages/download_docs.py
gitlab_versioned_pages/static/folder-solid.svg
gitlab_versioned_pages/static/style.css
gitlab_versioned_pages/templates/index.html
gitlab_versioned_pages-0.1.6.dist-info/LICENSE
gitlab_versioned_pages-0.1.6.dist-info/METADATA
gitlab_versioned_pages-0.1.6.dist-info/WHEEL
gitlab_versioned_pages-0.1.6.dist-info/top_level.txt
gitlab_versioned_pages-0.1.6.dist-info/RECORD
