Metadata-Version: 2.1
Name: gitlab-versioned-pages
Version: 0.1.6
Summary: Include documentation for multiple project versions in a single GitLab page
Home-page: https://gitlab.com/ostrokach/gitlab-versioned-pages
Author: Alexey Strokach
Author-email: alex.strokach@utoronto.ca
License: UNKNOWN
Keywords: gitlab_versioned_pages
Platform: UNKNOWN
Classifier: Intended Audience :: Developers
Classifier: Natural Language :: English
Classifier: Programming Language :: Python :: 3.7
Classifier: Programming Language :: Python :: 3.8
Classifier: Programming Language :: Python :: 3.9
Requires-Dist: jinja2
Requires-Dist: python-gitlab
